{
  "result": [
    {
      "locate" : "【花蓮縣】",
      "content" : "路上都不插國旗了 愛國心消退"
    },
    {
      "locate" : "【新北市】",
      "content" : "恕我大攔轎QQ"
    },
    {
      "locate" : "【新北市】",
      "content" : "地方的媽媽需要香菜"
    },
    {
      "locate" : "【南投縣】",
      "content" : "陸客不來了，害我交不到女朋友"
    },
    {
      "locate" : "【苗栗縣】",
      "content" : "苗栗客運不準時班次太少而且有些司機態度欠佳"
    },
    {
      "locate" : "【連江縣】",
      "content" : "大陸災民在此"
    },
    {
      "locate" : "【花蓮縣】",
      "content" : "寫信告訴我今天海是什麼顏色ˋ"
    },
    {
      "locate" : "【新北市】",
      "content" : "　何苦為了攔轎特地做了個網站 直接去剪綵現場不就行了嘛"
    },
    {
      "locate" : "【台東縣】",
      "content" : "太麻里隔壁~"
    },
    {
      "locate" : "【新北市】",
      "content" : "解放淪陷災區，人人有責"
    },
    {
      "locate" : "【新北市】",
      "content" : "房價怎麼居高不下，這樣讓淪陷災區的同胞怎麼購買呢？"
    },
    {
      "locate" : "【南投縣】",
      "content" : "只有家樂福QQ"
    }
  ]
}